quickbbee/README.md
quickbbee/__init__.py
quickbbee/bbee.py
quickbbee/EE_BB_models/README.md
quickbbee/EE_BB_models/cp_NN_BB.pkl
quickbbee/EE_BB_models/cp_NN_EE.pkl
quickbbee/tests/test_quickbbee.py
quickbbee-1.0.2.dist-info/LICENSE
quickbbee-1.0.2.dist-info/METADATA
quickbbee-1.0.2.dist-info/WHEEL
quickbbee-1.0.2.dist-info/top_level.txt
quickbbee-1.0.2.dist-info/RECORD
