Metadata-Version: 2.1
Name: quickbbee
Version: 1.0.2
Summary: This package enables faster calculations of EE and BB spectra, leveraging models trained on data generated by CAMB.
Home-page: https://github.com/jusdelio/QuickBBEE.git
Author: Emmanuel Rasolofo, Giulio Ganci
License: GNU General Public License v3.0
Classifier: Operating System :: OS Independent
Classifier: Intended Audience :: Developers
Classifier: Intended Audience :: Science/Research
License-File: LICENSE
Requires-Dist: cosmopower
Requires-Dist: tf-keras
